frapi/__init__.py
frapi/frapi_client.py
frapi/frapi_image.py
frapi/tf_client2.py
frapi-0.0.5.dist-info/LICENCE
frapi-0.0.5.dist-info/METADATA
frapi-0.0.5.dist-info/WHEEL
frapi-0.0.5.dist-info/top_level.txt
frapi-0.0.5.dist-info/RECORD
