Metadata-Version: 2.1
Name: frapi
Version: 0.0.5
Summary: Package for Face Recognition API
Home-page: https://github.com/BIG-CHENG/FaceRec
Author: BIG CHENG
Author-email: bigcheng.asus@gmail.com
License: UNKNOWN
Platform: UNKNOWN
Classifier: Programming Language :: Python :: 3
Classifier: License :: OSI Approved :: MIT License
Classifier: Operating System :: OS Independent
Requires-Dist: numpy
Requires-Dist: grpcio
Requires-Dist: tensorflow
Requires-Dist: tensorflow-serving-api
